{
  "slug": "angleconverter",
  "category": "converter",
  "icon": "📐",
  "script": "angleconverter.js",
  "widget": "<div id=\"ang-app\"><div class=\"row\"><div class=\"field\"><label for=\"ang-val\">{{ui.value}}</label><input type=\"number\" id=\"ang-val\" step=\"any\" value=\"180\" inputmode=\"decimal\"></div><div class=\"field\"><label for=\"ang-from\">{{ui.from}}</label><select id=\"ang-from\"></select></div><div class=\"field\"><label for=\"ang-to\">{{ui.to}}</label><select id=\"ang-to\"></select></div></div><div class=\"result\"><span class=\"big\" id=\"ang-out\">—</span></div></div>",
  "strings": {
    "en": {
      "title": "Angle Unit Converter",
      "metaDescription": "Free angle converter. Convert between degrees, radians, gradians, arcminutes, arcseconds, turns and milliradians instantly.",
      "h1": "Angle Unit Converter",
      "intro": "Convert angles between degrees, radians, gradians, arcminutes, arcseconds, turns and milliradians.",
      "faq_title": "Angle converter FAQ",
      "ui": {
        "value": "Value",
        "from": "From",
        "to": "To"
      },
      "faq": [
        {
          "q": "How many radians in a circle?",
          "a": "A full circle = 2π radians ≈ 6.2832 radians. Radians are the natural unit for angles in mathematics because they directly relate arc length to radius: arc = radius × angle in radians."
        },
        {
          "q": "What are gradians?",
          "a": "Gradians (also grads or gon) divide a full circle into 400 units, so a right angle = 100 gradians. Used primarily in surveying and civil engineering, especially in Europe. 90° = 100 grad = π/2 radians."
        },
        {
          "q": "What are arcminutes and arcseconds?",
          "a": "1 degree = 60 arcminutes ('). 1 arcminute = 60 arcseconds (\"). Used in navigation, astronomy and geographic coordinates. Latitude/longitude are often expressed as degrees, minutes, seconds (DMS). 1 arcsecond ≈ 31 metres on Earth's surface."
        }
      ]
    },
    "pt": {
      "title": "Conversor de Ângulo",
      "metaDescription": "Conversor de ângulo gratuito. Converta entre graus, radianos, gradianos, arcminutos, arcssegundos, voltas e miliradianos instantaneamente.",
      "h1": "Conversor de Ângulo",
      "intro": "Converta ângulos entre graus, radianos, gradianos, arcminutos, arcssegundos, voltas e miliradianos.",
      "faq_title": "Perguntas frequentes sobre conversor de ângulo",
      "ui": {
        "value": "Valor",
        "from": "De",
        "to": "Para"
      },
      "faq": [
        {
          "q": "Quantos radianos há em um círculo?",
          "a": "Um círculo completo = 2π radianos ≈ 6,2832 radianos. Radianos são a unidade natural para ângulos em matemática."
        },
        {
          "q": "O que são gradianos?",
          "a": "Gradianos dividem um círculo completo em 400 unidades, então um ângulo reto = 100 gradianos. Usados principalmente em levantamentos topográficos e engenharia civil."
        },
        {
          "q": "O que são arcminutos e arcssegundos?",
          "a": "1 grau = 60 arcminutos (min). 1 arcminuto = 60 arcssegundos (s). Usados em navegação, astronomia e coordenadas geográficas."
        }
      ]
    },
    "zh": {
      "title": "角度单位转换器 — 转换度、弧度、梯度等",
      "metaDescription": "自由角度转换器。立即在度、弧度、梯度、弧分、弧秒、圈数和毫弧度之间进行转换。",
      "h1": "角度单位转换器",
      "intro": "在度、弧度、梯度、弧分、弧秒、圈数和毫弧度之间转换角度。",
      "faq_title": "角度转换器常见问题解答",
      "ui": {
        "value": "价值",
        "from": "来自",
        "to": "至"
      },
      "faq": [
        {
          "q": "一个圆有多少弧度？",
          "a": "一个完整的圆 = 2π 弧度 ≈ 6.2832 弧度。弧度是数学中角度的自然单位，因为它们直接将弧长与半径联系起来：弧 = 半径 × 弧度角。"
        },
        {
          "q": "什么是梯度？",
          "a": "度数（也称为 grad 或 gon）将整圆分为 400 个单位，因此直角 = 100 度。主要用于测量和土木工程，特别是在欧洲。 90° = 100 度 = π/2 弧度。"
        },
        {
          "q": "什么是弧分和弧秒？",
          "a": "1 度 = 60 角分 (')。 1 角分 = 60 角秒 (\")。用于导航、天文学和地理坐标。纬度/经度通常表示为度、分、秒 (DMS)。1 角秒 ≈ 地球表面的 31 米。"
        }
      ]
    },
    "hi": {
      "title": "कोण इकाई कनवर्टर",
      "metaDescription": "फ्री एंगल कनवर्टर. डिग्री, रेडियन, ग्रेडियन, आर्कमिनट, आर्कसेकंड, टर्न और मिलिराडियन के बीच तुरंत कनवर्ट करें।",
      "h1": "कोण इकाई कनवर्टर",
      "intro": "कोणों को डिग्री, रेडियन, ग्रेडियन, आर्कमिनट, आर्कसेकंड, टर्न और मिलिरेडियन के बीच बदलें।",
      "faq_title": "कोण परिवर्तक अक्सर पूछे जाने वाले प्रश्न",
      "ui": {
        "value": "मूल्य",
        "from": "से",
        "to": "को"
      },
      "faq": [
        {
          "q": "एक वृत्त में कितने रेडियन होते हैं?",
          "a": "एक पूर्ण वृत्त = 2π रेडियन ≈ 6.2832 रेडियन। रेडियन गणित में कोणों के लिए प्राकृतिक इकाई हैं क्योंकि वे सीधे चाप की लंबाई को त्रिज्या से जोड़ते हैं: चाप = त्रिज्या × रेडियन में कोण।"
        },
        {
          "q": "ग्रेडियन क्या हैं?",
          "a": "ग्रेडियन (ग्रेड या गॉन भी) एक पूर्ण वृत्त को 400 इकाइयों में विभाजित करते हैं, इसलिए एक समकोण = 100 ग्रेडियन। मुख्य रूप से सर्वेक्षण और सिविल इंजीनियरिंग में उपयोग किया जाता है, खासकर यूरोप में। 90° = 100 ग्रेड = π/2 रेडियन।"
        },
        {
          "q": "आर्कमिनट और आर्कसेकंड क्या हैं?",
          "a": "1 डिग्री = 60 आर्कमिनट (')। 1 आर्कमिनट = 60 आर्कसेकंड (\")। नेविगेशन, खगोल विज्ञान और भौगोलिक निर्देशांक में उपयोग किया जाता है। अक्षांश/देशांतर को अक्सर डिग्री, मिनट, सेकंड (डीएमएस) के रूप में व्यक्त किया जाता है। 1 आर्कसेकंड ≈ पृथ्वी की सतह पर 31 मीटर।"
        }
      ]
    },
    "es": {
      "title": "Conversor de unidades de ángulo",
      "metaDescription": "Convertidor de ángulo libre. Convierta entre grados, radianes, gradianes, minutos de arco, segundos de arco, vueltas y milirradianes al instante.",
      "h1": "Convertidor de unidades de ángulo",
      "intro": "Convierta ángulos entre grados, radianes, gradianes, minutos de arco, segundos de arco, vueltas y milirradianes.",
      "faq_title": "Preguntas frecuentes sobre el convertidor de ángulo",
      "ui": {
        "value": "Valor",
        "from": "De",
        "to": "A"
      },
      "faq": [
        {
          "q": "¿Cuántos radianes hay en un círculo?",
          "a": "Un círculo completo = 2π radianes ≈ 6,2832 radianes. Los radianes son la unidad natural de los ángulos en matemáticas porque relacionan directamente la longitud del arco con el radio: arco = radio × ángulo en radianes."
        },
        {
          "q": "¿Qué son los graduados?",
          "a": "Los gradianes (también grads o gon) dividen un círculo completo en 400 unidades, por lo que un ángulo recto = 100 gradianes. Se utiliza principalmente en topografía e ingeniería civil, especialmente en Europa. 90° = 100 grados = π/2 radianes."
        },
        {
          "q": "¿Qué son los minutos de arco y los segundos de arco?",
          "a": "1 grado = 60 minutos de arco ('). 1 minuto de arco = 60 segundos de arco (\"). Se utiliza en navegación, astronomía y coordenadas geográficas. La latitud y longitud a menudo se expresan como grados, minutos, segundos (DMS). 1 segundo de arco ≈ 31 metros en la superficie de la Tierra."
        }
      ]
    },
    "fr": {
      "title": "Convertisseur d'unités d'angle",
      "metaDescription": "Convertisseur d'angle gratuit. Convertissez instantanément les degrés, radians, grades, minutes d'arc, secondes d'arc, tours et milliradians.",
      "h1": "Convertisseur d'unité d'angle",
      "intro": "Convertissez les angles entre degrés, radians, grades, minutes d'arc, secondes d'arc, tours et milliradians.",
      "faq_title": "FAQ sur les convertisseurs d'angle",
      "ui": {
        "value": "Valeur",
        "from": "De",
        "to": "À"
      },
      "faq": [
        {
          "q": "Combien de radians dans un cercle ?",
          "a": "Un cercle complet = 2π radians ≈ 6,2832 radians. Les radians sont l'unité naturelle des angles en mathématiques car ils relient directement la longueur de l'arc au rayon : arc = rayon × angle en radians."
        },
        {
          "q": "Que sont les grades ?",
          "a": "Les grades (également grades ou gon) divisent un cercle complet en 400 unités, donc un angle droit = ​​100 grades. Utilisé principalement en topographie et en génie civil, notamment en Europe. 90° = 100 degrés = π/2 radians."
        },
        {
          "q": "Que sont les minutes d'arc et les secondes d'arc ?",
          "a": "1 degré = 60 minutes d'arc ('). 1 minute d'arc = 60 secondes d'arc (\"). Utilisé en navigation, en astronomie et en coordonnées géographiques. La latitude/longitude est souvent exprimée en degrés, minutes, secondes (DMS). 1 seconde d'arc ≈ 31 mètres à la surface de la Terre."
        }
      ]
    },
    "ar": {
      "title": "محول وحدات الزاوية - تحويل الدرجات والراديان والتراديان",
      "metaDescription": "محول زاوية حر. التحويل بين الدرجات، والراديان، والتراديان، والدقائق القوسية، والثواني القوسية، والمنعطفات، والميليراديان على الفور.",
      "h1": "محول وحدة الزاوية",
      "intro": "تحويل الزوايا بين الدرجات والراديان والتراديان والدقائق القوسية والثواني القوسية والمنعطفات والمليراديان.",
      "faq_title": "الأسئلة الشائعة حول محول الزوايا",
      "ui": {
        "value": "القيمة",
        "from": "من",
        "to": "ل"
      },
      "faq": [
        {
          "q": "كم راديان في الدائرة؟",
          "a": "الدائرة الكاملة = 2π راديان ≈ 6.2832 راديان. الراديان هي الوحدة الطبيعية للزوايا في الرياضيات لأنها تربط بشكل مباشر طول القوس بنصف القطر: القوس = نصف القطر × الزاوية بالراديان."
        },
        {
          "q": "ما هي غراديان؟",
          "a": "يقسم التدرج (أيضًا الغراد أو الغون) الدائرة الكاملة إلى 400 وحدة، لذا فإن الزاوية القائمة = 100 تدرج. يستخدم في المقام الأول في المسح والهندسة المدنية، وخاصة في أوروبا. 90° = 100 غراد = π/2 راديان."
        },
        {
          "q": "ما هي الدقائق القوسية والثواني القوسية؟",
          "a": "1 درجة = 60 دقيقة قوسية ('). 1 دقيقة قوسية = 60 ثانية قوسية (\"). تستخدم في الملاحة وعلم الفلك والإحداثيات الجغرافية. غالبًا ما يتم التعبير عن خطوط الطول والعرض بالدرجات والدقائق والثواني (DMS). 1 ثانية قوسية ≈ 31 مترًا على سطح الأرض."
        }
      ]
    },
    "bn": {
      "title": "অ্যাঙ্গেল ইউনিট কনভার্টার",
      "metaDescription": "বিনামূল্যে কোণ রূপান্তরকারী. ডিগ্রী, রেডিয়ান, গ্রেডিয়ান, আর্কমিনিট, আর্কসেকেন্ড, টার্ন এবং মিলিরাডিয়ানের মধ্যে অবিলম্বে রূপান্তর করুন।",
      "h1": "অ্যাঙ্গেল ইউনিট কনভার্টার",
      "intro": "ডিগ্রি, রেডিয়ান, গ্রেডিয়ান, আর্কমিনিট, আর্কসেকেন্ড, টার্ন এবং মিলিরাডিয়ানের মধ্যে কোণগুলিকে রূপান্তর করুন।",
      "faq_title": "কোণ রূপান্তরকারী FAQ",
      "ui": {
        "value": "মান",
        "from": "থেকে",
        "to": "প্রতি"
      },
      "faq": [
        {
          "q": "একটি বৃত্তে কয়টি রেডিয়ান?",
          "a": "একটি পূর্ণ বৃত্ত = 2π রেডিয়ান ≈ 6.2832 রেডিয়ান। রেডিয়ান হল গণিতের কোণের প্রাকৃতিক একক কারণ তারা সরাসরি চাপের দৈর্ঘ্যকে ব্যাসার্ধের সাথে সম্পর্কিত করে: চাপ = ব্যাসার্ধ × রেডিয়ানে কোণ।"
        },
        {
          "q": "গ্রেডিয়ান কি?",
          "a": "গ্রেডিয়ান (এছাড়াও গ্রেড বা গন) একটি পূর্ণ বৃত্তকে 400 ইউনিটে ভাগ করে, তাই একটি সমকোণ = 100 গ্রেডিয়ান। বিশেষ করে ইউরোপে জরিপ এবং সিভিল ইঞ্জিনিয়ারিংয়ে প্রাথমিকভাবে ব্যবহৃত হয়। 90° = 100 গ্রেড = π/2 রেডিয়ান।"
        },
        {
          "q": "আর্কমিনিট এবং আর্কসেকেন্ড কি?",
          "a": "1 ডিগ্রি = 60 আর্কমিনিট (')। 1 আর্কমিনিট = 60 আর্কসেকেন্ড (\")। নেভিগেশন, জ্যোতির্বিদ্যা এবং ভৌগলিক স্থানাঙ্কে ব্যবহৃত হয়। অক্ষাংশ/দ্রাঘিমাংশ প্রায়ই ডিগ্রী, মিনিট, সেকেন্ড (DMS) হিসাবে প্রকাশ করা হয়। পৃথিবীর পৃষ্ঠে 1 আর্কসেকেন্ড ≈ 31 মিটার।"
        }
      ]
    },
    "ru": {
      "title": "Конвертер угловых единиц",
      "metaDescription": "Свободный преобразователь углов. Мгновенно конвертируйте градусы, радианы, градины, угловые минуты, угловые секунды, повороты и миллирадианы.",
      "h1": "Конвертер угловых единиц",
      "intro": "Преобразование углов между градусами, радианами, градианами, угловыми минутами, угловыми секундами, поворотами и миллирадианами.",
      "faq_title": "Часто задаваемые вопросы по угловому преобразователю",
      "ui": {
        "value": "Значение",
        "from": "От",
        "to": "Чтобы"
      },
      "faq": [
        {
          "q": "Сколько радиан в круге?",
          "a": "Полный круг = 2π радиан ≈ 6,2832 радиан. Радианы являются естественной единицей измерения углов в математике, поскольку они напрямую связывают длину дуги с радиусом: дуга = радиус × угол в радианах."
        },
        {
          "q": "Что такое градиенты?",
          "a": "Градианы (также грады или гоны) делят полный круг на 400 единиц, поэтому прямой угол = 100 градианам. Используется в основном в геодезии и гражданском строительстве, особенно в Европе. 90° = 100 град = π/2 радиан."
        },
        {
          "q": "Что такое угловые минуты и угловые секунды?",
          "a": "1 градус = 60 угловых минут ('). 1 угловая минута = 60 угловых секунд (\"). Используется в навигации, астрономии и географических координатах. Широта/долгота часто выражается в градусах, минутах, секундах (DMS). 1 угловая секунда ≈ 31 метр на поверхности Земли."
        }
      ]
    },
    "ur": {
      "title": "زاویہ یونٹ کنورٹر",
      "metaDescription": "مفت زاویہ کنورٹر۔ ڈگریوں، ریڈینز، گریڈینز، آرک منٹس، آرک سیکنڈز، موڑ اور ملیریڈینز کے درمیان فوری طور پر تبدیل کریں۔",
      "h1": "زاویہ یونٹ کنورٹر",
      "intro": "زاویوں کو ڈگریوں، ریڈینز، گریڈینز، آرک منٹس، آرک سیکنڈز، موڑ اور ملیریڈینز کے درمیان تبدیل کریں۔",
      "faq_title": "زاویہ کنورٹر اکثر پوچھے گئے سوالات",
      "ui": {
        "value": "قدر",
        "from": "سے",
        "to": "کو"
      },
      "faq": [
        {
          "q": "ایک دائرے میں کتنے ریڈین ہیں؟",
          "a": "ایک مکمل دائرہ = 2π ریڈینز ≈ 6.2832 ریڈینز۔ ریڈینز ریاضی میں زاویوں کی قدرتی اکائی ہیں کیونکہ وہ قوس کی لمبائی کا براہ راست رداس سے تعلق رکھتے ہیں: قوس = رداس × ریڈینز میں زاویہ۔"
        },
        {
          "q": "گریڈینز کیا ہیں؟",
          "a": "گریڈین (گریڈ یا گون بھی) ایک پورے دائرے کو 400 اکائیوں میں تقسیم کرتے ہیں، تو ایک صحیح زاویہ = 100 گریڈین۔ بنیادی طور پر سروے اور سول انجینئرنگ میں استعمال کیا جاتا ہے، خاص طور پر یورپ میں۔ 90° = 100 گریڈ = π/2 ریڈین۔"
        },
        {
          "q": "آرک منٹس اور آرک سیکنڈز کیا ہیں؟",
          "a": "1 ڈگری = 60 آرک منٹ (')۔ 1 آرک منٹ = 60 آرک سیکنڈز (\")۔ نیویگیشن، فلکیات اور جغرافیائی نقاط میں استعمال ہوتا ہے۔ عرض البلد/طول البلد کو اکثر ڈگری، منٹ، سیکنڈ (DMS) کے طور پر ظاہر کیا جاتا ہے۔ زمین کی سطح پر 1 آرک سیکنڈ ≈ 31 میٹر۔"
        }
      ]
    }
  }
}
