{
  "slug": "quadratic",
  "category": "math",
  "icon": "📈",
  "script": "quadratic.js",
  "widget": "<form id=\"quad-form\"><p style=\"opacity:0.7;font-size:0.9rem\">ax² + bx + c = 0</p><div class=\"row\"><div class=\"field\"><label for=\"quad-a\">a</label><input type=\"number\" id=\"quad-a\" step=\"any\" placeholder=\"1\" inputmode=\"decimal\"></div><div class=\"field\"><label for=\"quad-b\">b</label><input type=\"number\" id=\"quad-b\" step=\"any\" placeholder=\"-5\" inputmode=\"decimal\"></div><div class=\"field\"><label for=\"quad-c\">c</label><input type=\"number\" id=\"quad-c\" step=\"any\" placeholder=\"6\" inputmode=\"decimal\"></div><button class=\"btn\" type=\"submit\">{{ui.solve}}</button></div></form><div class=\"result\"><div id=\"quad-out\">—</div></div>",
  "strings": {
    "en": {
      "title": "Quadratic Equation Solver — find roots of ax² + bx + c = 0",
      "metaDescription": "Free quadratic equation solver. Enter a, b and c coefficients to find the roots of ax² + bx + c = 0 using the quadratic formula.",
      "h1": "Quadratic Equation Solver",
      "intro": "Enter the coefficients a, b and c of the equation ax² + bx + c = 0 and get the real (or complex) roots instantly.",
      "faq_title": "Quadratic equation FAQ",
      "ui": {
        "solve": "Solve"
      },
      "faq": [
        {
          "q": "What is the quadratic formula?",
          "a": "x = (−b ± √(b²−4ac)) / (2a). The term inside the square root, b²−4ac, is called the discriminant. If it is positive there are two real roots, zero means one repeated root, and negative means two complex roots."
        },
        {
          "q": "What are complex roots?",
          "a": "When the discriminant is negative, the square root of a negative number is imaginary. The roots have the form p ± qi where i = √(−1). Complex roots always come in conjugate pairs."
        },
        {
          "q": "What if a = 0?",
          "a": "If a = 0 the equation is not quadratic — it becomes linear: bx + c = 0, with solution x = −c/b."
        }
      ]
    },
    "pt": {
      "title": "Resolvedor de Equação Quadrática — encontre as raízes de ax² + bx + c = 0",
      "metaDescription": "Resolvedor de equação quadrática gratuito. Insira os coeficientes a, b e c para encontrar as raízes de ax² + bx + c = 0 usando a fórmula de Báskara.",
      "h1": "Resolvedor de Equação Quadrática",
      "intro": "Insira os coeficientes a, b e c da equação ax² + bx + c = 0 e obtenha as raízes reais (ou complexas) instantaneamente.",
      "faq_title": "Perguntas frequentes sobre equação quadrática",
      "ui": {
        "solve": "Resolver"
      },
      "faq": [
        {
          "q": "O que é a fórmula de Báskara?",
          "a": "x = (−b ± √(b²−4ac)) / (2a). O termo dentro da raiz quadrada, b²−4ac, é chamado de discriminante. Se positivo: duas raízes reais. Se zero: uma raiz repetida. Se negativo: duas raízes complexas."
        },
        {
          "q": "O que são raízes complexas?",
          "a": "Quando o discriminante é negativo, a raiz quadrada de um número negativo é imaginária. As raízes têm a forma p ± qi onde i = √(−1). Raízes complexas sempre vêm em pares conjugados."
        },
        {
          "q": "E se a = 0?",
          "a": "Se a = 0 a equação não é quadrática — torna-se linear: bx + c = 0, com solução x = −c/b."
        }
      ]
    },
    "zh": {
      "title": "二次方程求解器 — 求 ax² + bx + c = 0 的根",
      "metaDescription": "免费二次方程求解器。输入 a、b 和 c 系数，使用二次公式求 ax² + bx + c = 0 的根。",
      "h1": "二次方程求解器",
      "intro": "输入方程 ax² + bx + c = 0 的系数 a、b 和 c，立即得到实数（或复数）根。",
      "faq_title": "二次方程常见问题解答",
      "ui": {
        "solve": "解决"
      },
      "faq": [
        {
          "q": "一元二次公式是什么？",
          "a": "x = (−b ± √(b²−4ac)) / (2a)。平方根内的项 b²−4ac 称为判别式。如果为正则有两个实根，零则表示有一个重根，负则表示有两个复根。"
        },
        {
          "q": "什么是复根？",
          "a": "当判别式为负数时，负数的平方根为虚数。根的形式为 p ± qi，其中 i = √(−1)。复根总是成对出现。"
        },
        {
          "q": "如果a=0怎么办？",
          "a": "如果 a = 0，则方程不是二次方程，而是线性方程：bx + c = 0，解 x = −c/b。"
        }
      ]
    },
    "hi": {
      "title": "द्विघात समीकरण सॉल्वर - ax² + bx + c = 0 के मूल खोजें",
      "metaDescription": "मुफ़्त द्विघात समीकरण सॉल्वर। द्विघात सूत्र का उपयोग करके ax² + bx + c = 0 के मूल ज्ञात करने के लिए a, b और c गुणांक दर्ज करें।",
      "h1": "द्विघात समीकरण सॉल्वर",
      "intro": "समीकरण ax² + bx + c = 0 के गुणांक a, b और c दर्ज करें और तुरंत वास्तविक (या जटिल) मूल प्राप्त करें।",
      "faq_title": "द्विघात समीकरण अक्सर पूछे जाने वाले प्रश्न",
      "ui": {
        "solve": "हल करें"
      },
      "faq": [
        {
          "q": "द्विघात सूत्र क्या है?",
          "a": "x = (−b ± √(b²−4ac)) / (2a). वर्गमूल के अंदर का पद, b²−4ac, विवेचक कहलाता है। यदि यह धनात्मक है तो दो वास्तविक जड़ें हैं, शून्य का अर्थ है एक दोहराया हुआ मूल, और ऋणात्मक का अर्थ है दो जटिल जड़ें।"
        },
        {
          "q": "जटिल जड़ें क्या हैं?",
          "a": "जब विवेचक ऋणात्मक होता है, तो ऋणात्मक संख्या का वर्गमूल काल्पनिक होता है। जड़ों का रूप p ± qi है जहां i = √(−1) है। जटिल जड़ें हमेशा संयुग्मी जोड़े में आती हैं।"
        },
        {
          "q": "क्या होगा यदि a = 0?",
          "a": "यदि a = 0 समीकरण द्विघात नहीं है - यह रैखिक हो जाता है: bx + c = 0, समाधान x = −c/b के साथ।"
        }
      ]
    },
    "es": {
      "title": "Solucionador de ecuaciones cuadráticas: encuentra raíces de ax² + bx + c = 0",
      "metaDescription": "Solucionador gratuito de ecuaciones cuadráticas. Ingrese los coeficientes a, b y c para encontrar las raíces de ax² + bx + c = 0 usando la fórmula cuadrática.",
      "h1": "Solucionador de ecuaciones cuadráticas",
      "intro": "Ingresa los coeficientes a, b y c de la ecuación ax² + bx + c = 0 y obtén las raíces reales (o complejas) al instante.",
      "faq_title": "Preguntas frecuentes sobre ecuaciones cuadráticas",
      "ui": {
        "solve": "Resolver"
      },
      "faq": [
        {
          "q": "¿Cuál es la fórmula cuadrática?",
          "a": "x = (−b ± √(b²−4ac)) / (2a). El término dentro de la raíz cuadrada, b²−4ac, se llama discriminante. Si es positivo hay dos raíces reales, cero significa una raíz repetida y negativo significa dos raíces complejas."
        },
        {
          "q": "¿Qué son las raíces complejas?",
          "a": "Cuando el discriminante es negativo, la raíz cuadrada de un número negativo es imaginaria. Las raíces tienen la forma p ± qi donde i = √(−1). Las raíces complejas siempre vienen en pares conjugados."
        },
        {
          "q": "¿Qué pasa si a = 0?",
          "a": "Si a = 0 la ecuación no es cuadrática, se vuelve lineal: bx + c = 0, con solución x = −c/b."
        }
      ]
    },
    "fr": {
      "title": "Solveur d'équations quadratiques - trouver les racines de ax² + bx + c = 0",
      "metaDescription": "Solveur d'équation quadratique gratuit. Entrez les coefficients a, b et c pour trouver les racines de ax² + bx + c = 0 à l'aide de la formule quadratique.",
      "h1": "Solveur d'équation quadratique",
      "intro": "Entrez les coefficients a, b et c de l'équation ax² + bx + c = 0 et obtenez instantanément les racines réelles (ou complexes).",
      "faq_title": "FAQ sur l'équation quadratique",
      "ui": {
        "solve": "Résoudre"
      },
      "faq": [
        {
          "q": "Quelle est la formule quadratique ?",
          "a": "x = (−b ± √(b²−4ac)) / (2a). Le terme à l’intérieur de la racine carrée, b²−4ac, est appelé discriminant. S'il est positif, il y a deux racines réelles, zéro signifie une racine répétée et négatif signifie deux racines complexes."
        },
        {
          "q": "Que sont les racines complexes ?",
          "a": "Lorsque le discriminant est négatif, la racine carrée d’un nombre négatif est imaginaire. Les racines ont la forme p ± qi où je = √(−1). Les racines complexes se présentent toujours par paires conjuguées."
        },
        {
          "q": "Et si a = 0 ?",
          "a": "Si a = 0 l'équation n'est pas quadratique — elle devient linéaire : bx + c = 0, avec solution x = −c/b."
        }
      ]
    },
    "ar": {
      "title": "حل المعادلات التربيعية — ابحث عن جذور ax² + bx + c = 0",
      "metaDescription": "حل المعادلات التربيعية الحرة. أدخل المعاملات a وb وc لإيجاد جذور ax² + bx + c = 0 باستخدام الصيغة التربيعية.",
      "h1": "حل المعادلات التربيعية",
      "intro": "أدخل المعاملات a وb وc للمعادلة ax² + bx + c = 0 واحصل على الجذور الحقيقية (أو المعقدة) على الفور.",
      "faq_title": "الأسئلة الشائعة حول المعادلة التربيعية",
      "ui": {
        "solve": "حل"
      },
      "faq": [
        {
          "q": "ما هي الصيغة التربيعية؟",
          "a": "x = (−b ± √(b²−4ac)) / (2a). يُطلق على الحد الموجود داخل الجذر التربيعي، b²−4ac، اسم المميز. إذا كان موجبًا، فهناك جذرين حقيقيين، والصفر يعني جذرًا واحدًا متكررًا، والسالب يعني جذرين معقدين."
        },
        {
          "q": "ما هي الجذور المعقدة؟",
          "a": "عندما يكون المميز سالبًا، يكون الجذر التربيعي لعدد سالب وهميًا. الجذور لها الشكل p ± qi حيث i = √(−1). تأتي الجذور المعقدة دائمًا في أزواج مترافقة."
        },
        {
          "q": "ماذا لو كان أ = 0؟",
          "a": "إذا كانت a = 0 فإن المعادلة ليست تربيعية — تصبح خطية: bx + c = 0، مع الحل x = −c/b."
        }
      ]
    },
    "bn": {
      "title": "দ্বিঘাত সমীকরণ সমাধান — ax² + bx + c = 0 এর মূল খুঁজুন",
      "metaDescription": "বিনামূল্যে দ্বিঘাত সমীকরণ সমাধানকারী। দ্বিঘাত সূত্র ব্যবহার করে ax² + bx + c = 0 এর শিকড় খুঁজে পেতে a, b এবং c সহগ লিখুন।",
      "h1": "দ্বিঘাত সমীকরণ সমাধানকারী",
      "intro": "ax² + bx + c = 0 সমীকরণের a, b এবং c সহগগুলি লিখুন এবং তাত্ক্ষণিকভাবে বাস্তব (বা জটিল) মূলগুলি পান।",
      "faq_title": "দ্বিঘাত সমীকরণ FAQ",
      "ui": {
        "solve": "সমাধান করুন"
      },
      "faq": [
        {
          "q": "দ্বিঘাত সূত্র কি?",
          "a": "x = (−b ± √(b²−4ac)) / (2a)। বর্গমূল, b²−4ac এর ভিতরের শব্দটিকে বৈষম্যকারী বলা হয়। যদি এটি ইতিবাচক হয় তবে দুটি বাস্তব মূল আছে, শূন্য মানে একটি পুনরাবৃত্ত মূল এবং ঋণাত্মক মানে দুটি জটিল মূল।"
        },
        {
          "q": "জটিল শিকড় কি?",
          "a": "যখন বৈষম্যকারী ঋণাত্মক হয়, তখন একটি ঋণাত্মক সংখ্যার বর্গমূল কাল্পনিক হয়। শিকড়ের আকার p ± qi যেখানে i = √(−1)। জটিল শিকড় সবসময় সংযোজিত জোড়ায় আসে।"
        },
        {
          "q": "a = 0 হলে কি হবে?",
          "a": "যদি a = 0 সমীকরণটি দ্বিঘাত না হয় — এটি রৈখিক হয়: bx + c = 0, সমাধান x = −c/b সহ।"
        }
      ]
    },
    "ru": {
      "title": "Решатель квадратных уравнений — найдите корни ax² + bx + c = 0",
      "metaDescription": "Бесплатный решатель квадратных уравнений. Введите коэффициенты a, b и c, чтобы найти корни ax² + bx + c = 0, используя квадратичную формулу.",
      "h1": "Решатель квадратных уравнений",
      "intro": "Введите коэффициенты a, b и c уравнения ax² + bx + c = 0 и мгновенно получите действительные (или комплексные) корни.",
      "faq_title": "Часто задаваемые вопросы по квадратным уравнениям",
      "ui": {
        "solve": "Решить"
      },
      "faq": [
        {
          "q": "Что такое квадратичная формула?",
          "a": "х = (−b ± √(b²−4ac)) / (2a). Член внутри квадратного корня b²−4ac называется дискриминантом. Если оно положительное, то имеется два действительных корня, ноль означает один повторяющийся корень, а отрицательное означает два комплексных корня."
        },
        {
          "q": "Что такое сложные корни?",
          "a": "Когда дискриминант отрицательный, квадратный корень из отрицательного числа является мнимым. Корни имеют вид p ± qi, где i = √(−1). Комплексные корни всегда встречаются сопряженными парами."
        },
        {
          "q": "Что, если а = 0?",
          "a": "Если a = 0, уравнение не является квадратным — оно становится линейным: bx + c = 0, с решением x = −c/b."
        }
      ]
    },
    "ur": {
      "title": "Quadratic Equation Solver — ax² + bx + c = 0 کی جڑیں تلاش کریں۔",
      "metaDescription": "مفت چوکور مساوات حل کرنے والا۔ چوکور فارمولے کا استعمال کرتے ہوئے ax² + bx + c = 0 کی جڑیں تلاش کرنے کے لیے a، b اور c کوفیشینٹس درج کریں۔",
      "h1": "چوکور مساوات حل کرنے والا",
      "intro": "مساوات ax² + bx + c = 0 کے گتانک a, b اور c درج کریں اور حقیقی (یا پیچیدہ) جڑیں فوری طور پر حاصل کریں۔",
      "faq_title": "چوکور مساوات FAQ",
      "ui": {
        "solve": "حل کریں۔"
      },
      "faq": [
        {
          "q": "چوکور فارمولا کیا ہے؟",
          "a": "x = (−b ± √(b²−4ac)) / (2a)۔ مربع جڑ کے اندر کی اصطلاح، b²−4ac، کو امتیازی کہا جاتا ہے۔ اگر یہ مثبت ہے تو دو حقیقی جڑیں ہیں، صفر کا مطلب ہے ایک بار بار جڑیں، اور منفی کا مطلب ہے دو پیچیدہ جڑیں۔"
        },
        {
          "q": "پیچیدہ جڑیں کیا ہیں؟",
          "a": "جب امتیاز کرنے والا منفی ہوتا ہے، تو منفی نمبر کا مربع جڑ خیالی ہوتا ہے۔ جڑوں کی شکل p ± qi ہے جہاں i = √(−1)۔ پیچیدہ جڑیں ہمیشہ کنجوگیٹ جوڑوں میں آتی ہیں۔"
        },
        {
          "q": "کیا ہوگا اگر a = 0؟",
          "a": "اگر a = 0 مساوات چوکور نہیں ہے — یہ لکیری ہو جاتی ہے: bx + c = 0، حل x = −c/b کے ساتھ۔"
        }
      ]
    }
  }
}
