{
  "slug": "workdays",
  "category": "time",
  "icon": "📅",
  "script": "workdays.js",
  "widget": "<form id=\"wd-form\"><div class=\"row\"><div class=\"field\"><label for=\"wd-from\">{{ui.from_date}}</label><input type=\"date\" id=\"wd-from\"></div><div class=\"field\"><label for=\"wd-to\">{{ui.to_date}}</label><input type=\"date\" id=\"wd-to\"></div></div><div class=\"result\"><span class=\"hint\">{{ui.workdays}}: </span><span class=\"big\" id=\"wd-out\">—</span></div><div id=\"wd-detail\" style=\"opacity:0.7;font-size:0.9rem;margin-top:0.5rem\"></div></form>",
  "strings": {
    "en": {
      "title": "Work Days Calculator — count business days between two dates",
      "metaDescription": "Free work days calculator. Count the number of business days (Monday–Friday) between any two dates, excluding weekends. Instant results in your browser.",
      "h1": "Work Days Calculator",
      "intro": "Select a start and end date to count the working days between them, excluding weekends.",
      "faq_title": "Work days FAQ",
      "ui": {
        "from_date": "Start date",
        "to_date": "End date",
        "workdays": "Working days"
      },
      "faq": [
        {
          "q": "Does this include public holidays?",
          "a": "No. This calculator excludes only weekends (Saturday and Sunday). Public holidays vary by country and cannot be determined automatically without knowing your location."
        },
        {
          "q": "Are the start and end dates included?",
          "a": "Yes, both the start and end dates are included if they fall on a weekday."
        },
        {
          "q": "Can I calculate workdays in the past?",
          "a": "Yes, enter any two dates in any order and the calculator returns the correct count."
        }
      ]
    },
    "pt": {
      "title": "Calculadora de Dias Úteis — conte dias úteis entre duas datas",
      "metaDescription": "Calculadora de dias úteis gratuita. Conte o número de dias úteis (segunda a sexta) entre quaisquer duas datas, excluindo fins de semana.",
      "h1": "Calculadora de Dias Úteis",
      "intro": "Selecione uma data de início e fim para contar os dias úteis entre elas, excluindo fins de semana.",
      "faq_title": "Perguntas frequentes de dias úteis",
      "ui": {
        "from_date": "Data inicial",
        "to_date": "Data final",
        "workdays": "Dias úteis"
      },
      "faq": [
        {
          "q": "Isso inclui feriados?",
          "a": "Não. Esta calculadora exclui apenas fins de semana (sábado e domingo). Feriados variam por país e não podem ser determinados automaticamente sem saber sua localização."
        },
        {
          "q": "As datas de início e fim são incluídas?",
          "a": "Sim, as datas de início e fim são incluídas se caírem em dia útil."
        },
        {
          "q": "Posso calcular dias úteis no passado?",
          "a": "Sim, informe quaisquer duas datas em qualquer ordem e a calculadora retorna a contagem correta."
        }
      ]
    }
  }
}
